git_ai/__init__.py
git_ai/cli.py
git_ai/core.py
git_ai/remote.py
git_ai/tracker.py
git_ai/visualizer.py
git_ai_tracker-0.1.0.dist-info/licenses/LICENSE
git_ai_tracker-0.1.0.dist-info/METADATA
git_ai_tracker-0.1.0.dist-info/WHEEL
git_ai_tracker-0.1.0.dist-info/entry_points.txt
git_ai_tracker-0.1.0.dist-info/top_level.txt
git_ai_tracker-0.1.0.dist-info/RECORD
