Metadata-Version: 2.4
Name: git-ai-tracker
Version: 0.1.0
Summary: A Git extension for tracking AI-made changes with sub-nodes and sub-branches
Author-email: João Galego <jgalego1990@gmail.com>
License-Expression: MIT
Project-URL: Homepage, https://github.com/jgalego/git-ai
Project-URL: Repository, https://github.com/jgalego/git-ai.git
Project-URL: Issues, https://github.com/jgalego/git-ai/issues
Project-URL: Documentation, https://github.com/jgalego/git-ai/blob/main/README.md
Classifier: Development Status :: 4 - Beta
Classifier: Intended Audience :: Developers
Classifier: Programming Language :: Python :: 3
Classifier: Programming Language :: Python :: 3.8
Classifier: Programming Language :: Python :: 3.9
Classifier: Programming Language :: Python :: 3.10
Classifier: Programming Language :: Python :: 3.11
Classifier: Programming Language :: Python :: 3.12
Classifier: Topic :: Software Development :: Version Control :: Git
Classifier: Topic :: Software Development :: Libraries :: Python Modules
Classifier: Environment :: Console
Classifier: Operating System :: POSIX
Classifier: Operating System :: MacOS
Requires-Python: >=3.8
License-File: LICENSE
Provides-Extra: dev
Requires-Dist: pytest>=6.0; extra == "dev"
Requires-Dist: pytest-cov>=2.10; extra == "dev"
Requires-Dist: black>=21.0; extra == "dev"
Requires-Dist: isort>=5.0; extra == "dev"
Requires-Dist: flake8>=3.8; extra == "dev"
Requires-Dist: mypy>=0.800; extra == "dev"
Dynamic: license-file
